air_pollution_check.py
air_pollution_check-0.1.9.dist-info/LICENSE
air_pollution_check-0.1.9.dist-info/WHEEL
air_pollution_check-0.1.9.dist-info/METADATA
air_pollution_check-0.1.9.dist-info/RECORD
