Metadata-Version: 2.1
Name: air-pollution-check
Version: 0.1.9
Summary: A package for looking into the air pollution data, which can transfer the data into dataframe, add in the overall air pollution to the dataframe, visualize the air pollution data, and output the pollution level comparison from the past to the future for a specific location.
License: MIT
Author: Yazhao Huang
Requires-Python: >=3.9,<4.0
Classifier: License :: OSI Approved :: MIT License
Classifier: Programming Language :: Python :: 3
Classifier: Programming Language :: Python :: 3.9
Classifier: Programming Language :: Python :: 3.10
Requires-Dist: pandas (>=1.5.2,<2.0.0)
